<algorithm_specification>
  <name>CIW-NN</name>
  <nParameters>9</nParameters>
  <seed>1</seed>
  <nOutput>1</nOutput>
  <parameter>
    <name>K</name>
    <type>integer</type>
    <domain>
      <lowerB>1</lowerB>
      <upperB>30</upperB>
    </domain>
    <default>1</default>
  </parameter>
  <parameter>
    <name>evals</name>
    <type>integer</type>
    <domain>
      <lowerB>100</lowerB>
      <upperB>1000000</upperB>
    </domain>
    <default>10000</default>
  </parameter>
  <parameter>
    <name>sizePop</name>
    <type>integer</type>
    <domain>
      <lowerB>10</lowerB>
      <upperB>200</upperB>
    </domain>
    <default>50</default>
  </parameter>
  <parameter>
    <name>alpha</name>
    <type>real</type>
    <domain>
      <lowerB>0</lowerB>
      <upperB>1</upperB>
    </domain>
    <default>0.5</default>
  </parameter>
  <parameter>
    <name>prob0to1</name>
    <type>real</type>
    <domain>
      <lowerB>0</lowerB>
      <upperB>1</upperB>
    </domain>
    <default>0.25</default>
  </parameter>
 <parameter>
    <name>prob1</name>
    <type>real</type>
    <domain>
      <lowerB>0</lowerB>
      <upperB>1</upperB>
    </domain>
    <default>0.25</default>
  </parameter>
  <parameter>
    <name>mut</name>
    <type>real</type>
    <domain>
      <lowerB>0</lowerB>
      <upperB>1</upperB>
    </domain>
    <default>0.05</default>
  </parameter>
  <parameter>
    <name>EpochFW</name>
    <type>integer</type>
    <domain>
      <lowerB>10</lowerB>
      <upperB>200</upperB>
    </domain>
    <default>40</default>
  </parameter>
  <parameter>
    <name>EpochIW</name>
    <type>integer</type>
    <domain>
      <lowerB>10</lowerB>
      <upperB>200</upperB>
    </domain>
    <default>40</default>
  </parameter>
</algorithm_specification>
