<algorithm_specification>
  <name>Fuzzy and Random Sets Modeling</name>
  <nParameters>5</nParameters>
  <seed>1</seed>
  <nOutput>0</nOutput>
  <parameter>
    <name>subAlgorithm</name>
    <type>list</type>
    <domain>
      <item>ModelFSS98</item>
    </domain>
    <default>ModelFSS98</default>
    <disabled/>
  </parameter>
  <parameter>
    <name>dataformat</name>
    <type>list</type>
    <domain>
      <item>keel</item>
    </domain>
    <default>keel</default>
    <disabled/>
  </parameter>
  <parameter>
    <name>outlabel</name>
    <type>list</type>
    <domain>
      <item>FSS98</item>
    </domain>
    <default>FSS98</default>
    <disabled/>
  </parameter>
  <parameter>
    <name>numrules</name>
    <type>integer</type>
    <domain>
      <lowerB>1</lowerB>
      <upperB>100</upperB>
    </domain>
    <default>1</default>
  </parameter>
  <parameter>
    <name>sigmafss98</name>
    <type>real</type>
    <domain>
      <lowerB>0.0001</lowerB>
      <upperB>10</upperB>
    </domain>
    <default>0.0001</default>
  </parameter>
</algorithm_specification>
